timeitpoj/__init__.py
timeitpoj/reporting/__init__.py
timeitpoj/reporting/events/__init__.py
timeitpoj/reporting/events/print_report_action.py
timeitpoj/reporting/summary.py
timeitpoj/reporting/task_report.py
timeitpoj/reporting/timeit_event.py
timeitpoj/timeit.py
timeitpoj/timer/__init__.py
timeitpoj/timer/internal_timer.py
timeitpoj/timer/timer.py
timeitpoj/utils/__init__.py
timeitpoj/utils/constants.py
timeitpoj/utils/misc.py
timeitpoj-0.1.11.dist-info/METADATA
timeitpoj-0.1.11.dist-info/WHEEL
timeitpoj-0.1.11.dist-info/entry_points.txt
timeitpoj-0.1.11.dist-info/RECORD
