Metadata-Version: 2.1
Name: timeitpoj
Version: 0.1.11
Summary: yet another random library for measuring python performance
Home-page: https://github.com/jvanmelckebeke/timeitpoj
License: MIT
Keywords: timeit,performance,benchmark,time,measure
Author: Jari Van Melckebeke
Author-email: jarivanmelckebeke@gmail.com
Maintainer: Jari Van Melckebeke
Maintainer-email: jarivanmelckebeke@gmail.com
Requires-Python: >=3.8,<4.0
Classifier: Intended Audience :: Developers
Classifier: License :: OSI Approved :: MIT License
Classifier: Programming Language :: Python :: 3
Classifier: Programming Language :: Python :: 3.8
Classifier: Programming Language :: Python :: 3.9
Classifier: Programming Language :: Python :: 3.10
Classifier: Programming Language :: Python :: 3.11
Classifier: Programming Language :: Python :: 3.12
Classifier: Topic :: System :: Logging
Classifier: Topic :: System :: Networking :: Monitoring
Classifier: Topic :: Utilities
Project-URL: Repository, https://github.com/jvanmelckebeke/timeitpoj
